wowool/apps/cypher/__init__.py
wowool/apps/cypher/config.py
wowool/apps/entity_graph/__init__.py
wowool/apps/entity_graph/config.py
wowool/cypher/app_id.py
wowool/cypher/cypher.py
wowool/cypher/cypher_stream.py
wowool/entity_graph/__init__.py
wowool/entity_graph/app_id.py
wowool/entity_graph/entity_graph.py
wowool/entity_graph/objects.py
wowool/entity_graph/resolve_variable.py
wowool/tools/entity_graph/__main__.py
wowool/tools/entity_graph/argument_parser.py
wowool/tools/entity_graph/cli.py
wowool/tools/entity_graph/movie_file_lnk_new_format.json
wowool_entity_graph-3.1.5.dist-info/METADATA
wowool_entity_graph-3.1.5.dist-info/WHEEL
wowool_entity_graph-3.1.5.dist-info/entry_points.txt
wowool_entity_graph-3.1.5.dist-info/top_level.txt
wowool_entity_graph-3.1.5.dist-info/RECORD
