Metadata-Version: 2.4
Name: wowool-entity-graph
Version: 3.1.5
Summary: Wowool Entity Graph
Home-page: https://www.wowool.com/
Author: Wowool
Author-email: info@wowool.com
Requires-Python: >=3.10
Dynamic: author
Dynamic: author-email
Dynamic: description
Dynamic: description-content-type
Dynamic: home-page
Dynamic: requires-python
Dynamic: summary
